quant_reporter/__init__.py
quant_reporter/analysis.py
quant_reporter/combined_report.py
quant_reporter/data.py
quant_reporter/html_builder.py
quant_reporter/metrics.py
quant_reporter/opt_core.py
quant_reporter/opt_plotting.py
quant_reporter/optimization.py
quant_reporter/plotting.py
quant_reporter/validation.py
quant_reporter-1.0.5.dist-info/licenses/LICENSE
quant_reporter-1.0.5.dist-info/METADATA
quant_reporter-1.0.5.dist-info/WHEEL
quant_reporter-1.0.5.dist-info/top_level.txt
quant_reporter-1.0.5.dist-info/RECORD
