Metadata-Version: 2.4
Name: quant_reporter
Version: 1.0.5
Summary: A Python module to generate quantitative finance reports.
Author-email: Manan Bansal <mananpbansal@gmail.com>
License: MIT License
Project-URL: Homepage, https://github.com/manan-tech/quant_reporter
Project-URL: Issues, https://github.com/manan-tech/quant_reporter/issues
Classifier: License :: OSI Approved :: MIT License
Classifier: Programming Language :: Python :: 3
Classifier: Programming Language :: Python :: 3.8
Classifier: Programming Language :: Python :: 3.9
Classifier: Programming Language :: Python :: 3.10
Classifier: Programming Language :: Python :: 3.11
Classifier: Intended Audience :: Developers
Classifier: Intended Audience :: Financial and Insurance Industry
Classifier: Operating System :: OS Independent
Classifier: Topic :: Office/Business :: Financial :: Investment
Requires-Python: >=3.8
License-File: LICENSE
Requires-Dist: pandas
Requires-Dist: numpy
Requires-Dist: yfinance
Requires-Dist: matplotlib
Requires-Dist: plotly
Requires-Dist: scipy
Requires-Dist: seaborn
Dynamic: license-file
